odoo/addons/account_partner_reconcile/README.rst
odoo/addons/account_partner_reconcile/__init__.py
odoo/addons/account_partner_reconcile/__manifest__.py
odoo/addons/account_partner_reconcile/i18n/account_partner_reconcile.pot
odoo/addons/account_partner_reconcile/models/__init__.py
odoo/addons/account_partner_reconcile/models/res_partner.py
odoo/addons/account_partner_reconcile/static/description/icon.png
odoo/addons/account_partner_reconcile/tests/__init__.py
odoo/addons/account_partner_reconcile/tests/test_account_partner_reconcile.py
odoo/addons/account_partner_reconcile/views/res_partner_view.xml
odoo11_addon_account_partner_reconcile-11.0.1.0.1.99.dev1.dist-info/METADATA
odoo11_addon_account_partner_reconcile-11.0.1.0.1.99.dev1.dist-info/RECORD
odoo11_addon_account_partner_reconcile-11.0.1.0.1.99.dev1.dist-info/WHEEL
odoo11_addon_account_partner_reconcile-11.0.1.0.1.99.dev1.dist-info/top_level.txt
